ndg/__init__.py
ndg/httpsclient/LICENSE
ndg/httpsclient/__init__.py
ndg/httpsclient/https.py
ndg/httpsclient/ssl_context_util.py
ndg/httpsclient/ssl_peer_verification.py
ndg/httpsclient/ssl_socket.py
ndg/httpsclient/subj_alt_name.py
ndg/httpsclient/urllib2_build_opener.py
ndg/httpsclient/utils.py
ndg/httpsclient/test/README
ndg/httpsclient/test/__init__.py
ndg/httpsclient/test/test_https.py
ndg/httpsclient/test/test_urllib2.py
ndg/httpsclient/test/test_utils.py
ndg/httpsclient/test/pki/localhost.crt
ndg/httpsclient/test/pki/localhost.key
ndg/httpsclient/test/pki/ca/7e15277f.0
ndg/httpsclient/test/scripts/openssl_https_server.sh
ndg_httpsclient-0.5.0.dist-info/METADATA
ndg_httpsclient-0.5.0.dist-info/RECORD
ndg_httpsclient-0.5.0.dist-info/WHEEL
ndg_httpsclient-0.5.0.dist-info/entry_points.txt
ndg_httpsclient-0.5.0.dist-info/top_level.txt
