Metadata-Version: 1.1
Name: ndg_httpsclient
Version: 0.5.0
Summary: Provides enhanced HTTPS support for httplib and urllib2 using PyOpenSSL
Home-page: https://github.com/cedadev/ndg_httpsclient/
Author: Richard Wilkinson and Philip Kershaw
Author-email: Philip.Kershaw@stfc.ac.uk
License: BSD - See ndg/httpsclient/LICENCE file for details
Platform: UNKNOWN
Classifier: Development Status :: 5 - Production/Stable
Classifier: Environment :: Console
Classifier: Environment :: Web Environment
Classifier: Intended Audience :: End Users/Desktop
Classifier: Intended Audience :: Developers
Classifier: Intended Audience :: System Administrators
Classifier: Intended Audience :: Science/Research
Classifier: License :: OSI Approved :: BSD License
Classifier: Natural Language :: English
Classifier: Operating System :: Microsoft :: Windows
Classifier: Operating System :: POSIX :: Linux
Classifier: Programming Language :: Python
Classifier: Programming Language :: Python :: 3
Classifier: Topic :: Security
Classifier: Topic :: Internet
Classifier: Topic :: Scientific/Engineering
Classifier: Topic :: System :: Distributed Computing
Classifier: Topic :: System :: Systems Administration :: Authentication/Directory
Classifier: Topic :: Software Development :: Libraries :: Python Modules
